mactop/__init__.py
mactop/const.py
mactop/layout_loader.py
mactop/layouts/__init__.py
mactop/main.py
mactop/metrics_source/__init__.py
mactop/metrics_source/ioreg.py
mactop/metrics_source/powermetrics.py
mactop/metrics_source/psutil_manager.py
mactop/metrics_store.py
mactop/panels/__init__.py
mactop/panels/_base.py
mactop/panels/battery.py
mactop/panels/cpu_freq.py
mactop/panels/cpu_percpu_usage.py
mactop/panels/cpu_total_usage_bar.py
mactop/panels/cpu_total_usage_text.py
mactop/panels/disk.py
mactop/panels/energy.py
mactop/panels/loadavg.py
mactop/panels/m1_cpu.py
mactop/panels/m1_gpu.py
mactop/panels/m1cpu_freq.py
mactop/panels/network_iobyte_rate_text.py
mactop/panels/network_iopacket_rate_text.py
mactop/panels/network_sparkline.py
mactop/panels/sensors.py
mactop/panels/swap_memory.py
mactop/panels/tasks.py
mactop/panels/uptime.py
mactop/panels/virtual_memory.py
mactop/themes/m1.xml
mactop/themes/mactop.xml
mactop/utils/__init__.py
mactop/utils/formatting.py
mactop/utils/rwlock.py
mactop/widgets/__init__.py
mactop/widgets/colorbar.py
mactop/widgets/dynamic_text.py
mactop/widgets/header.py
mactop/widgets/labeled_colorbar.py
mactop/widgets/labeled_progress.py
mactop/widgets/labeled_sparkline.py
mactop/widgets/labeled_vstringbar.py
mactop/widgets/vstringbar.py
mactop-0.1.11.dist-info/LICENSE
mactop-0.1.11.dist-info/METADATA
mactop-0.1.11.dist-info/WHEEL
mactop-0.1.11.dist-info/entry_points.txt
mactop-0.1.11.dist-info/RECORD
