Metadata-Version: 2.1
Name: mactop
Version: 0.1.11
Summary: Htop for macbook.
Author: laixintao
Author-email: laixintaoo@gmail.com
Requires-Python: >=3.10,<4.0
Classifier: Programming Language :: Python :: 3
Classifier: Programming Language :: Python :: 3.10
Classifier: Programming Language :: Python :: 3.11
Classifier: Programming Language :: Python :: 3.12
Requires-Dist: click (>=8.1.7,<9.0.0)
Requires-Dist: psutil (>=5.9.5,<6.0.0)
Requires-Dist: textual (>=0.35.1,<0.36.0)
